pytest_soft_assert/__init__.py
pytest_soft_assert/plugin.py
pytest_soft_assert/soft_assert.py
pytest_soft_assert-0.0.0rc0.dist-info/entry_points.txt
pytest_soft_assert-0.0.0rc0.dist-info/WHEEL
pytest_soft_assert-0.0.0rc0.dist-info/METADATA
pytest_soft_assert-0.0.0rc0.dist-info/RECORD
