Metadata-Version: 2.4
Name: pytest-soft-assert
Version: 0.0.0rc0
Summary: Pytest plugin for soft assertions.
Keywords: pytest
Author-email: Harmin Parra Rueda <harmin.rueda@gmail.com>
Requires-Python: >=3.11
Classifier: Framework :: Pytest
Classifier: License :: OSI Approved :: MIT License
Classifier: Topic :: Software Development :: Quality Assurance
Classifier: Topic :: Software Development :: Testing
Requires-Dist: pytest >= 8.4.0
